LICENSE
MANIFEST.in
setup.cfg
setup.py
lib/__init__.py
lib/address.py
lib/cidr.py
lib/compat.py
martinellis.egg-info/PKG-INFO
martinellis.egg-info/SOURCES.txt
martinellis.egg-info/dependency_links.txt
martinellis.egg-info/requires.txt
martinellis.egg-info/top_level.txt