Metadata-Version: 1.1
Name: martinellis
Version: 1.2.9
Summary: A python library for manipulating IPv4 and IPv6 addresses.
Home-page: https://github.com/frank2/martinellis
Author: frank2
Author-email: frank2@dc949.org
License: GPLv3
Keywords: cidr ip ipv4 ipv6
Platform: UNKNOWN
Classifier: Development Status :: 5 - Production/Stable
Classifier: Topic :: Internet
Classifier: Topic :: Software Development :: Libraries
Classifier: License :: OSI Approved :: GNU General Public License v3 (GPLv3)
